direct/__init__.py
direct/directutil/DirectMySQLdb.py
direct/directutil/DirectMySQLdbConnection.py
direct/directutil/LargeBlobSenderConsts.py
direct/directutil/DeltaProfiler.py
direct/directutil/DistributedLargeBlobSender.py
direct/directutil/Mopath.py
direct/directutil/Verify.py
direct/directutil/DistributedLargeBlobSenderAI.py
direct/directutil/WeightedChoice.py
direct/directutil/MemoryLeakHelpers.py
direct/directutil/__init__.py
direct/distributed/DoInterestManager.py
direct/distributed/DistributedCameraOV.py
direct/distributed/CachedDOData.py
direct/distributed/DistributedCartesianGrid.py
direct/distributed/TimeManagerAI.py
direct/distributed/ParentMgr.py
direct/distributed/DistributedObjectGlobal.py
direct/distributed/ClientRepository.py
direct/distributed/AsyncRequest.py
direct/distributed/DistributedObjectGlobalAI.py
direct/distributed/InterestWatcher.py
direct/distributed/DistributedNode.py
direct/distributed/CRDataCache.py
direct/distributed/GridParent.py
direct/distributed/DoCollectionManager.py
direct/distributed/TimeManager.py
direct/distributed/DistributedObjectGlobalUD.py
direct/distributed/PyDatagram.py
direct/distributed/direct.dc
direct/distributed/CartesianGridBase.py
direct/distributed/ConnectionRepository.py
direct/distributed/StagedObject.py
direct/distributed/DistributedObjectUD.py
direct/distributed/DistributedObjectAI.py
direct/distributed/MsgTypesCMU.py
direct/distributed/DistributedCamera.py
direct/distributed/DistributedSmoothNodeBase.py
direct/distributed/ServerRepository.py
direct/distributed/DistributedNodeUD.py
direct/distributed/DistributedCartesianGridAI.py
direct/distributed/DistributedObject.py
direct/distributed/DistributedObjectBase.py
direct/distributed/ClockDelta.py
direct/distributed/DistributedObjectOV.py
direct/distributed/DistributedSmoothNodeAI.py
direct/distributed/GridChild.py
direct/distributed/DistributedCameraAI.py
direct/distributed/PyDatagramIterator.py
direct/distributed/DistributedNodeAI.py
panda3d-1.10.16.dist-info/entry_points.txt
panda3d-1.10.16.dist-info/metadata.json
panda3d-1.10.16.dist-info/METADATA
panda3d-1.10.16.dist-info/WHEEL
panda3d-1.10.16.dist-info/LICENSE.txt
panda3d-1.10.16.dist-info/README.md
panda3d-1.10.16.dist-info/top_level.txt
panda3d-1.10.16.dist-info/RECORD
