Metadata-Version: 2.1
Name: Panda3D
Version: 1.10.16
Summary: Panda3D is a framework for 3D rendering and game development for Python and C++ programs.
License: Modified BSD License
Home-page: https://www.panda3d.org/
Project-URL: Tracker, https://github.com/panda3d/panda3d/issues
Project-URL: Funding, https://opencollective.com/panda3d
Project-URL: Documentation, https://www.panda3d.org/manual/
Project-URL: Source, https://github.com/panda3d/panda3d
Project-URL: Download, https://www.panda3d.org/download/
Author: Panda3D Team
Author-email: etc-panda3d@lists.andrew.cmu.edu
Platform: macosx_10_9_x86_64
Classifier: Development Status :: 5 - Production/Stable
Classifier: Intended Audience :: Developers
Classifier: Intended Audience :: End Users/Desktop
Classifier: License :: OSI Approved :: BSD License
Classifier: Operating System :: OS Independent
Classifier: Programming Language :: C++
Classifier: Programming Language :: Python
Classifier: Programming Language :: Python :: 2
Classifier: Programming Language :: Python :: 2.7
Classifier: Programming Language :: Python :: 3
Classifier: Programming Language :: Python :: 3.4
Classifier: Programming Language :: Python :: 3.5
Classifier: Programming Language :: Python :: 3.6
Classifier: Programming Language :: Python :: 3.7
Classifier: Programming Language :: Python :: 3.8
Classifier: Programming Language :: Python :: 3.9
Classifier: Programming Language :: Python :: 3.10
Classifier: Programming Language :: Python :: 3.11
Classifier: Programming Language :: Python :: 3.12
Classifier: Programming Language :: Python :: 3.13
Classifier: Programming Language :: Python :: 3.14
Classifier: Programming Language :: Python :: Implementation :: CPython
Classifier: Topic :: Games/Entertainment
Classifier: Topic :: Multimedia
Classifier: Topic :: Multimedia :: Graphics
Classifier: Topic :: Multimedia :: Graphics :: 3D Rendering
Classifier: Topic :: Software Development :: Libraries
Classifier: Topic :: Software Development :: Libraries :: Application Frameworks
Classifier: Topic :: Software Development :: Libraries :: Python Modules
